[{"id":492099,"filename":"tlg0527.tlg010.opp-grc2","tokens":"ΚΑΙ ἐγένετο ἐν τῷ κρίνειν τοὺς κριτὰς καὶ ἐγένετο λιμὸς ἐν τῆ γῆ·","lemmas":"καί γίγνομαι ἐν τῷ κρίνω ὁ κριτής καί γίγνομαι  ἐν  γῆ ·"},{"id":492100,"filename":"tlg0527.tlg010.opp-grc2","tokens":"καὶ ἐπορεύθη ἀνὴρ ἀπὸ Βαιθλέεμ τῆς ᾿Ιούδα τοῦ παροικῆσαι ἐν ἀγρῷ Μωάβ, αὐτὸς καὶ ἡ γυνὴ αὐτοῦ καὶ οἱ υἱοὶ αὐτοῦ.","lemmas":"καί ἐφορεύω ἀνήρ ἀπό  ὁ  ὁ παροικέω ἐν ἀγρός  , αὐτός καί ὁ γυνή αὐτός καί ὁ υἱός αὐτός ."},{"id":492101,"filename":"tlg0527.tlg010.opp-grc2","tokens":"καὶ ὄνομα τῷ ἀνδρὶ ᾿Αβειμέλεχ, καὶ ὄνομα τοῖς δυσὶν υἱοῖς αὐτοῦ Μααλὼν καὶ ών, ᾿Εφραθαῖοι ἐκ Βαιθλέεμ τῆς Ἰούδα·","lemmas":"καί ὄνομα τῷ ἀνήρ  , καί ὄνομα ὁ  υἱός αὐτός  καί  ,  ἐκ  ὁ  ·"},{"id":492102,"filename":"tlg0527.tlg010.opp-grc2","tokens":"καὶ ἥλθοσαν εἰς ἀγρὸν καὶ ἦσαν ἐκεῖ.","lemmas":"καί  εἰς ἀγρός καί εἰμί ἐκεῖ ."},{"id":492103,"filename":"tlg0527.tlg010.opp-grc2","tokens":"καὶ ἀπέθανεν ᾿Αβειμέλεχ ὁ ἀνὴρ τῆς Νωεμείν, καὶ κατελείφθη αὕτη καὶ οἱ δύο υἱοὶ αὐτῆς.","lemmas":"καί ἀποθνῄσκω  ὁ ἀνήρ ὁ  , καί καταλείπω οὗτος καί ὁ γε υἱός αὐτός ."},{"id":492104,"filename":"tlg0527.tlg010.opp-grc2","tokens":"καὶ ἐλάβοσαν ἑαυτοῖς γυναῖκας Μωαβείτιδας·","lemmas":"καί  ἑαυτοῦ γυνή  ·"},{"id":492105,"filename":"tlg0527.tlg010.opp-grc2","tokens":"ὄνομα τῇ μιᾷ ᾿Ορφά, καὶ ὄνομα τῇ δευτέρᾳ ῾Ρούθ·","lemmas":"ὄνομα ὁ   , καί ὄνομα ὁ δεύτερος  ·"},{"id":492106,"filename":"tlg0527.tlg010.opp-grc2","tokens":"καὶ κατῴκησαν ἐκεῖ ὡς δέκα ἔτη.","lemmas":"καί κατοικέω ἐκεῖ ὡς  ἔτος ."},{"id":492107,"filename":"tlg0527.tlg010.opp-grc2","tokens":"καὶ ἀπέθανον καί γε ἀμφότεροι, Μααλὼν καὶ Χελαιών·","lemmas":"καί ἀποθνῄσκω καί γε ἀμφότερος ,  καί  ·"},{"id":492108,"filename":"tlg0527.tlg010.opp-grc2","tokens":"καὶ κατελείφθη ἡ γυνὴ ἀπὸ τοῦ ἀνδρὸς αὐτῆς καὶ ἀπὸ τῶν δύο υἱῶν αὐτῆς.","lemmas":"καί καταλείπω ὁ γυνή ἀπό ὁ ἀνήρ αὐτός καί ἀπό ὁ γε υἱός αὐτός ."},{"id":492109,"filename":"tlg0527.tlg010.opp-grc2","tokens":"Καὶ ἀνέστη αὕτη καὶ αἱ δύο νύμφαι αὐτῆς καὶ ἀπέστρεψαν ἐξ ἀγροῦ Μωάβ, ὅτι ἤκουσαν ἐν ἀγρῷ Μωὰβ ὅτι ᾿Επέσκεπται Κύριος τὸν λαὸν αὐτοῦ, δοῦναι αὐτοῖς ἄρτους.","lemmas":"καί ἀνίστημι οὗτος καί ὁ γε νύμφη αὐτός καί ἀποστρέφω ἐκ ἀγρός  , ὅτι2 ἀκούω ἐν ἀγρός  ὅτι2  κύριος2 ὁ λαός αὐτός , δίδωμι αὐτός ἄρτος ."},{"id":492110,"filename":"tlg0527.tlg010.opp-grc2","tokens":"καὶ ἐξῆλθεν ἐκ τοῦ τόπου οὗ ἦν ἐκεῖ, καὶ αἱ δύο νύμφαι αὐτῆς μετ’ αὐτῆς·","lemmas":"καί ἐξέρχομαι ἐκ ὁ  οὗ εἰμί ἐκεῖ , καί ὁ γε νύμφη αὐτός μετά αὐτός ·"},{"id":492111,"filename":"tlg0527.tlg010.opp-grc2","tokens":"καὶ ἐπορεύοντο ἐν τῇ ὁδῷ τοῦ ἐπιστρέψαι εἰς τὴν γῆν Ἰούδα.","lemmas":"καί ἐφορεύω ἐν ὁ ὁδός ὁ ἐπιστρέφω εἰς ὁ γῆ  ."},{"id":492112,"filename":"tlg0527.tlg010.opp-grc2","tokens":"καὶ εἶπεν Νωεμεὶν ταῖς νύμφαις αὐτῆς Πορεύεσθε δή, ἀποστράφητε ἑκάστη εἰς οἶκον μητρὸς αὐτῆς·","lemmas":"καί λέγω  ὁ νύμφη αὐτός  δή ,  ἕκαστος εἰς οἶκος μήτηρ αὐτός ·"},{"id":492113,"filename":"tlg0527.tlg010.opp-grc2","tokens":"ποιήσαι κύριος μεθ’ ὑμῶν ἔλεος, καθὼς ἐποιήσατε μετὰ τῶν τεθνηκότων καὶ μετ’ ἐμοῦ·","lemmas":"ποιέω κύριος2 μετά ὑμός  ,  ποιέω μετά ὁ ἀποθνῄσκω καί μετά ἐμός ·"},{"id":492114,"filename":"tlg0527.tlg010.opp-grc2","tokens":"δῴη κύριος ὑμῖν καὶ εὕροιτε ἀνάπαυσιν, ἑκάστη ἐν οἴκῳ ἀνδρὸς αὐτῆς.","lemmas":"κύριος2  καί εὑρίσκω ἀνάπαυσις , ἕκαστος ἐν οἶκος ἀνήρ αὐτός ."},{"id":492115,"filename":"tlg0527.tlg010.opp-grc2","tokens":"καὶ κατεφίλησεν αὐτάς·","lemmas":"καί καταφιλέω αὐτός ·"},{"id":492116,"filename":"tlg0527.tlg010.opp-grc2","tokens":"καὶ ἐπῆραν τὴν φωνὴν αὐτῶν καὶ ἔκλαυσαν.","lemmas":"καί  ὁ φωνή αὐτός καί κλαίω ."},{"id":492117,"filename":"tlg0527.tlg010.opp-grc2","tokens":"καὶ εἶπαν αὐτῇ Μετὰ σοῦ ἐπιστρέφομεν εἰς τὸν λαόν σου.","lemmas":"καί λέγω αὐτός μετά   εἰς ὁ λαός  ."},{"id":492118,"filename":"tlg0527.tlg010.opp-grc2","tokens":"καὶ εἶπεν Νωεμείν ᾿Επιστράφητε δή, θυγατέρες μου·","lemmas":"καί λέγω   δή , θυγάτηρ  ·"},{"id":492119,"filename":"tlg0527.tlg010.opp-grc2","tokens":"καὶ ἵνα τί πορεύεσθε μετ’ ἑ μοῦ;","lemmas":"καί ἵνα τι πορεύω μετά ἕ  ;"},{"id":492120,"filename":"tlg0527.tlg010.opp-grc2","tokens":"μὴ ἔτι μοι υἱοὶ ἐν τῇ κοιλίᾳ μου, καὶ ἔσονται ὑμίν εἰς ἄνδρας;","lemmas":"μή ἔτι   ἐν ὁ κοιλία  , καί εἰμί  εἰς ἀνήρ ;"},{"id":492121,"filename":"tlg0527.tlg010.opp-grc2","tokens":"ἐπιστράφητε δή, θυγατέρες μου, διότι γεγήρακα τοῦ μὴ εἶναι ἀνδρί·","lemmas":"δή , θυγάτηρ  , διότι  ὁ μή εἰμί ἀνήρ ·"},{"id":492122,"filename":"tlg0527.tlg010.opp-grc2","tokens":"ὅτι εἶπα ὅτι ἔστιν μοι ὑπόστασις τοῦ γενηθῆναί με ἀνδρὶ καὶ τέξομαι υἱούς, μὴ αὐτοὺς προσδέξεσθε ἕως οὗ ἁδρυνθῶσιν;","lemmas":"ὅτι2  ὅτι2 εἰμί  ὑπόστασις ὁ   ἀνήρ καί τίκτω υἱός , μή αὐτός  ἕως οὗ  ;"},{"id":492123,"filename":"tlg0527.tlg010.opp-grc2","tokens":"ἢ αὐτοῖς κατασχεθήσεσθε τοῦ μὴ γενέσθαι ἀνδρί;","lemmas":"τίη αὐτός  ὁ μή γίγνομαι ἀνήρ ;"},{"id":492124,"filename":"tlg0527.tlg010.opp-grc2","tokens":"μὴ δὴ θυγατέρες μου, ὅτι ἐπικράνθη μοι ὑπὲρ ὑμᾶς, ὅτι ἐξῆλθεν ἐν ἐμοὶ χεὶρ Κυρίου.","lemmas":"δή θυγάτηρ  , ὅτι2 ἐπικραίνω  ὑπέρ  , ὅτι2 ἐξέρχομαι ἐν  χείρ  ."},{"id":492125,"filename":"tlg0527.tlg010.opp-grc2","tokens":"καὶ ἐπῆραν τὴν φωνὴν αὐτῶν καὶ ἔκλαυσαν ἔτι·","lemmas":"καί  ὁ φωνή αὐτός καί κλαίω ἔτι ·"},{"id":492126,"filename":"tlg0527.tlg010.opp-grc2","tokens":"καὶ κατεφίλησεν Ορφὰ τὴν πενθερὰν αὐτῆς καὶ ἐπέστρεψεν εἰς τὸν λαὸν αὐτῆς, ῾Ροὺθ δὲ ἠκολούθησεν αὐτῇ.","lemmas":"καί καταφιλέω  ὁ  αὐτός καί ἐπιστρέφω εἰς ὁ λαός αὐτός ,  δέ ἀκολουθέω αὐτός ."},{"id":492127,"filename":"tlg0527.tlg010.opp-grc2","tokens":"καὶ εἶπεν Νωεμεὶν πρός ῾Ρούθ ἰδοὺ ἀνέστρεψεν σύννυμφός σου πρὸς λαὸν αὐτῆς καὶ πρὸς τοὺς θεοὺς αὐτῆς.","lemmas":"καί λέγω  πρός   ἀναστρέφω   πρός λαός αὐτός καί πρός ὁ  αὐτός ."},{"id":492128,"filename":"tlg0527.tlg010.opp-grc2","tokens":"ἐπιστράφητι δὴ καὶ σὺ ὀπίσω τῆς συννύμφου σου.","lemmas":"δή καί  ὀπίσω ὁ   ."},{"id":492129,"filename":"tlg0527.tlg010.opp-grc2","tokens":"εἶπεν δὲ ῾Ρούθ Μὴ ἀπαντήσαι ἐμοὶ τοῦ καταλιπεῖν σε ἡ ἀποστρέψαι ὄπισθέν σου, ὅτι σὺ ὅπου ἐὰν πορευθῇς πορεύσομαι, καἰ οὗ ἐὰν αὐλισθῇς αὐλισθήσομαι.","lemmas":"λέγω δέ  μή   ὁ καταλείπω  ὁ ἀποστρέφω   , ὅτι2  ὅπου ἐάν  πορεύω ,  οὗ ἐάν   ."},{"id":492130,"filename":"tlg0527.tlg010.opp-grc2","tokens":"ὁ λαός σου λαός μου, καὶ ὁ θεός σου θεός μου·","lemmas":"ὁ λαός  λαός  , καί ὁ θεός  θεός  ·"},{"id":492131,"filename":"tlg0527.tlg010.opp-grc2","tokens":"καὶ οὗ ἐὰν ἀποθάνῃς ἀποθανοῦμαι, κἀκεῖ ταφήσομαι.","lemmas":"καί οὗ ἐάν ἀποθνῄσκω  , ἐκεῖ  ."},{"id":492132,"filename":"tlg0527.tlg010.opp-grc2","tokens":"τάδε ποιήσαι μοι Κύριος καὶ τάδε προσθείη, ὅτι θάνατος διαστελεῖ ἀνὰ μέσον ἐμοῦ καὶ σοῦ.","lemmas":"ὅδε ποιέω  κύριος2 καί ὅδε  , ὅτι2 θάνατος  ἀνά μέσος  καί σός ."},{"id":492133,"filename":"tlg0527.tlg010.opp-grc2","tokens":"ἰδοῦσα δὲ Νωεμεὶν ὅτι κραταιοῦται αὐτὴ τοῦ πορεύεσθαι μετ’ αὐτῆς, ἐκόπασεν τοῦ λαλῆσαι πρὸς αὐτὴν ἔτι ᾿Επορεύθησαν δὲ ἀμφότεραι ἕως τοῦ παραγενέσθαι αὐτὰς εἰς Βαιθλέεμ.","lemmas":"ὁράω δέ  ὅτι2  αὐτός ὁ πορεύω μετά αὐτός , κοπάζω ὁ λαλέω πρός αὐτός ἔτι  δέ ἀμφότερος ἕως ὁ παραγίγνομαι αὐτός εἰς  ."},{"id":492134,"filename":"tlg0527.tlg010.opp-grc2","tokens":"καὶ ἤχησεν πᾶσα ἡ πόλις ἐπ’ αὐτῆς, κοὶ εἶπον Αὕτη ἐστὶν Νωεμείν;","lemmas":"καί  πᾶς ὁ πόλις ἐπί αὐτός ,  λέγω  εἰμί  ;"},{"id":492135,"filename":"tlg0527.tlg010.opp-grc2","tokens":"καὶ εἶπεν πρὸς αὐτάς Μὴ δὴ καλεῖτέ με Νωεμείν, καλέσατέ με πικράν, ὅτι ἐπικράνθη ἐν ἐμοὶ ὁ ἱκανὸς σφόδρα.","lemmas":"καί λέγω πρός αὐτός μή δή καλέω   ,   πικρός , ὅτι2 ἐπικραίνω ἐν  ὁ ἱκανός σφόδρα ."},{"id":492136,"filename":"tlg0527.tlg010.opp-grc2","tokens":"ἐγὼ πλήρης ἐπορεύθην, κοὶ κενὴν ἀπέ- στρεψέν με ὁ κύριος·","lemmas":"πλήρης ἐφορεύω ,  κενός  -  ἐγώ ὁ κύριος2 ·"},{"id":492137,"filename":"tlg0527.tlg010.opp-grc2","tokens":"καὶ ἵνα τί καλεῖτέ με Νωεμείν, καὶ ἐταπείνωσέν με, καὶ ὁ ἱκανὸς ἐκάκωσέν με,.","lemmas":"καί ἵνα τι καλέω   , καί  ἐγώ , καί ὁ ἱκανός   , ."},{"id":492138,"filename":"tlg0527.tlg010.opp-grc2","tokens":"καὶ ἐπέ Νωεμεὶν καὶ ῾Ροὺθ ἡ Μωαβεῖτις ἡ νύμφη αὐτῆς ἐπιστρέφουσα ἀγροῦ Μωάβ·","lemmas":"καί   καί  ὁ  ὁ νύμφη αὐτός ἐπιστρέφω ἀγρός  ·"},{"id":492139,"filename":"tlg0527.tlg010.opp-grc2","tokens":"αὗται δὲ παρεγενήθησαν εἰς Βαιθλέεμ ἐν ἁρχῇ θερισμοῦ κριθῶν.","lemmas":"οὗτος δέ παραγίγνομαι εἰς  ἐν  θερισμός κριθή ."},{"id":492140,"filename":"tlg0527.tlg010.opp-grc2","tokens":"Καὶ τῇ Νωεμεὶν ἀνὴρ γνώριμος τῷ ἀνδρὶ αὐτῆς·","lemmas":"ὁ  ἀνήρ γνώριμος τῷ ἀνήρ αὐτός ·"},{"id":492141,"filename":"tlg0527.tlg010.opp-grc2","tokens":"ὁ δὲ ἀνὴρ δυνατὸς ἐκ τῆς συγγενίας ᾿Αβειμέλεχ, καὶ ὄνομα αὐτῶ Βόος.","lemmas":"ὁ δέ ἀνήρ δυνατός ἐκ ὁ   , καί ὄνομα   ."},{"id":492142,"filename":"tlg0527.tlg010.opp-grc2","tokens":"καὶ ἡ Μωαβεῖτις τοῖς στάχυσιν κατόπισθεν οὗ ἐὰν εὕρω χάριν ἐν ὀφθαλμοῖς αὐτοῦ.","lemmas":"καί ὁ  ὁ  κατόπισθεν οὗ ἐάν  χάρις ἐν ὀφθαλμός αὐτός ."},{"id":492143,"filename":"tlg0527.tlg010.opp-grc2","tokens":"εἶπεν δὲ αὐτῇ Πορεύου, θυγάτηρ.","lemmas":"λέγω δέ αὐτός  , θυγάτηρ ."},{"id":492144,"filename":"tlg0527.tlg010.opp-grc2","tokens":"καὶ ἐπορεύθη, καὶ συνέλεξεν ἐν τῷ ἀγρῷ κατόπισθεν τῶν τῶν θεριζόντων·","lemmas":"καί ἐφορεύω , καί συλλέγω ἐν ὁ ἀγρός κατόπισθεν ὁ ὁ θερίζω ·"},{"id":492145,"filename":"tlg0527.tlg010.opp-grc2","tokens":"καὶ περιέπεσεν περιπτώματι τῇ μερίδι τοῦ ἀγροῦ Βόος, τοῦ ἐκ συγγενείας ᾿Αβειμέλεχ·","lemmas":"καί περιπίπτω  ὁ μερίς ὁ ἀγρός  , ὁ ἐκ συγγένεια  ·"},{"id":492146,"filename":"tlg0527.tlg010.opp-grc2","tokens":"Καὶ ἰδοὺ Βόος ἦλθεν ἐκ Βαιθλέεμ καὶ εἶπεν τοῖς θερίζουσιν Κύριος μεθ’ ὑμῶν·","lemmas":"καί   ἔρχομαι ἐκ  καί λέγω ὁ θερίζω κύριος2 μετά ὑμός ·"},{"id":492147,"filename":"tlg0527.tlg010.opp-grc2","tokens":"κοὶ εἶπον αὐτῷ Εὐλογήσαι σε Κύριος.","lemmas":"λέγω αὐτός   κύριος2 ."},{"id":492148,"filename":"tlg0527.tlg010.opp-grc2","tokens":"καὶ εἶπεν Βόος τῷ παιδαρίῳ αὐτοῦ τῷ ἐφεστῶτι ἐπὶ τοὺς θερίζοντας τίνος ἡ νεᾶνις αὕτη;","lemmas":"καί λέγω  τῷ  αὐτός τῷ ἐφίστημι ἐπί ὁ θερίζω τις ὁ νεᾶνις οὗτος ;"},{"id":492149,"filename":"tlg0527.tlg010.opp-grc2","tokens":"καὶ ἀπεκρίθη τὸ παιδάριον τὸ ἐφεστὸς ἐπὶ τούς θερίζοντας καὶ εἶπεν Ἡ παῖς ἡ Μωαβεῖτίς ἐστιν, ἡ ἀποστραφεῖσα μετὰ Νωεμεὶν ἐξ ἀγροῦ Μωάβ·","lemmas":"καί ἀποκρίνω ὁ παιδάριον ὁ  ἐπί ὁ θερίζω καί λέγω ὁ παῖς ὁ  εἰμί , ὁ  μετά  ἐκ ἀγρός  ·"},{"id":492150,"filename":"tlg0527.tlg010.opp-grc2","tokens":"καὶ εἶπεν Συλλέξω δὴ καὶ συνάξω ἐν τοῖς δράγμασιν ὄπισθεν τῶν θεριζόντων·","lemmas":"καί λέγω  δή καί συνάγνυμι ἐν ὁ  ὄπισθεν ὁ θερίζω ·"},{"id":492151,"filename":"tlg0527.tlg010.opp-grc2","tokens":"καὶ ἦλθεν καὶ ἔστη ἀπὸ πρωίθεν καὶ ἕως ἑσπέρας, οὐ κατέπαυσεν ἐν τῷ ἀγρῷ μικρόν.","lemmas":"καί ἔρχομαι καί ἵστημι ἀπό  καί ἕως ἑσπέρα , οὐ καταπαύω ἐν ὁ ἀγρός μικρός ."},{"id":492152,"filename":"tlg0527.tlg010.opp-grc2","tokens":"καὶ εἶπεν Βόος πρὸς ῾Ρούθ οὐκ ἤκουσας, θυγάτηρ;","lemmas":"καί λέγω  πρός  οὐ ἀκούω , θυγάτηρ ;"},{"id":492153,"filename":"tlg0527.tlg010.opp-grc2","tokens":"μὴ πορευθῇς ἐν ἀγρῷ συλλέξαι ἑτέρῳ·","lemmas":"μή  ἐν ἀγρός συλλέγω ἕτερος ·"},{"id":492154,"filename":"tlg0527.tlg010.opp-grc2","tokens":"καὶ σὺ οὐ πορεύσῃ ἐντεῦθεν, ὧδε κολλήθητι μετὰ τῶν κορασίων μου.","lemmas":"καί σύ οὐ πορεύω ἐντεῦθεν , ὧδε  μετά ὁ   ."},{"id":492155,"filename":"tlg0527.tlg010.opp-grc2","tokens":"οἱ ὀφθαλμοί σου εἰς τὸν ἀγρὸν οὗ ἐὰν θερίζωσιν, καὶ πορεύση κατόπισθεν αὐτῶν.","lemmas":"ὁ ὀφθαλμός  εἰς ὁ ἀγρός οὗ ἐάν  , καί   αὐτός ."},{"id":492156,"filename":"tlg0527.tlg010.opp-grc2","tokens":"ἰδοὺ ἐνετειλάμην τοῖς παιδαρίοις τοῦ μὴ ἅψασθαὶ σου·","lemmas":"ὁ παιδάριον ὁ μή   ·"},{"id":492157,"filename":"tlg0527.tlg010.opp-grc2","tokens":"καὶ ὅ τι διψήσεις, καὶ πορευθήσῃ εἰς τὰ σκεύη καὶ πίεσαι ὅθεν ἀν’ ὑδρεύωνται τὰ παιδάρια.","lemmas":"καί ὅς τις  , καί  εἰς ὁ σκεῦος καί πιέζω ὅθεν ἀνά ’  ὁ παιδάριον ."},{"id":492158,"filename":"tlg0527.tlg010.opp-grc2","tokens":"καὶ ἔπεσεν ἐπὶ πρόσωπον αὐτῆς καὶ προσεκύνησεν ἑ’ πὶ τὴν γῆν, καὶ εἶπεν πρὸς αὐτόν Τί ὅτι εὗρον χάριν ἐν ὀφθαλμοῖς σου τοῦ ἐπιγνῶναί με, καὶ ἐγώ εἰμι ξένη;","lemmas":"καί ἐφέζομαι ἐπί πρόσωπον αὐτός καί προσκυνέω ἕ ’  ὁ γῆ , καί λέγω πρός αὐτός  ὅτι2 εὑρίσκω χάρις ἐν ὀφθαλμός  ὁ   , καί  εἰμί  ;"},{"id":492159,"filename":"tlg0527.tlg010.opp-grc2","tokens":"καὶ ἀπεκρίθη Βόοσ καὶ εἶπεν αὐτῇ ᾿Απαγγελίᾳ ἀπηγγέλη μοι ὅσα πεποίηκας μετὰ τῆς πενθερᾶς σου μετὰ τὸ ἀποθανεῖν τὸν ἄνδρα σου, καὶ πῶς κατέλιπες τὸν πατέρα σου καὶ τὴν μητέρα σου καὶ τὴν γῆν γενέσεως σου, καὶ ἐπορεύθης πρὸς λαὸν ὃν οὐκ ᾔδεις ἐχθὲς καὶ τρίτης.","lemmas":"καί ἀποκρίνω  καί λέγω αὐτός    ὅσος ποιέω μετά ὁ   μετά ὁ ἀποθνῄσκω ὁ ἀνήρ  , καί πῶς καταλείπω ὁ πατήρ  καί ὁ μήτηρ  καί ὁ γῆ γένεσις  , καί  πρός λαός  οὐ   καί  ."},{"id":492160,"filename":"tlg0527.tlg010.opp-grc2","tokens":"ἀποτίσαι κύριος τὴν ἐργασίαν σου·","lemmas":"ἀποτίνω κύριος2 ὁ ἐργασία  ·"},{"id":492161,"filename":"tlg0527.tlg010.opp-grc2","tokens":"γένοιτο ὁ μισθός σου πλήρης παρὰ κυρίου θεοῦ ᾿Ισραήλ, πρὸς ὅν ἦλθες πεποιθέναι ὑπὸ τὰς πτέρυγας αὐτοῦ ἡ δὲ εἶπεν Εὔροιμι χάριν ἐν ὀφθαλμοῖς σου, κύριε, ὅτι παρεκάλεσάς με, καὶ ὅτι ἐλάλησας ἐπὶ καρδίαν τῆς δούλης σου, καὶ ἰδοὺ ἐγὼ ἔσομαι ὡς μία τῶν παιδισκῶν σου.","lemmas":"γίγνομαι ὁ μισθός  πλήρης παρά  θεός  , πρός ὅς ἔρχομαι πείθω ὑπό ὁ πτέρυξ αὐτός ὁ δέ λέγω  χάρις ἐν ὀφθαλμός  , κύριος , ὅτι2  ἐγώ , καί ὅτι2  ἐπί καρδία ὁ δούλη  , καί    ὡς  ὁ παιδίσκη  ."},{"id":492162,"filename":"tlg0527.tlg010.opp-grc2","tokens":"καὶ εἶπεν αὐτῇ Βόος Ἤδη ὥρα τοῦ Φαγεῖν, πρόσελθε ὧδε καὶ φάγεσαι τῶν ἄρτων, καὶ βάψεις τὸν ψωμόν σου τῷ ὄξει.","lemmas":"καί λέγω αὐτός   ὥρα2 ὁ ἐσθίω , προσέρχομαι ὧδε καί  ὁ  , καί  ὁ ψωμός  ὁ ὄξος ."},{"id":492163,"filename":"tlg0527.tlg010.opp-grc2","tokens":"καὶ ἐκάθισεν ῾Ροὺθ ἐκ πλαγίων τῶν θεριζόντων·","lemmas":"καί καθίζω  ἐκ πλάγιον ὁ θερίζω ·"},{"id":492164,"filename":"tlg0527.tlg010.opp-grc2","tokens":"καὶ ἐβούνισεν αὐτῇ Βόος ἄλφιτον, κα ἔφαγεν καὶ ἐνεπλήσθη καὶ κατέλιπεν, καὶ ἀνέστη τοῦ συλλέγειν.","lemmas":"καί  αὐτός   ,   καί ἐμπίμπλημι καί καταλείπω , καί ἀνίστημι ὁ συλλέγω ."},{"id":492165,"filename":"tlg0527.tlg010.opp-grc2","tokens":"καὶ ἐνετείλατο βοὸς τοῖς παιδαρίοις αὐτοῦ λέγων καί γε ἀνὰ μέσον τῶν δραγμάτων συλλεγέτω, καὶ μὴ καταισχύνητε αὐτήν·","lemmas":"καί ἐντέλλω  ὁ παιδάριον αὐτός λέγω καί γε ἀνά μέσος ὁ δράγμα  , καί μή καταισχύνω αὐτός ·"},{"id":492166,"filename":"tlg0527.tlg010.opp-grc2","tokens":"καὶ βαστάζοντες βαστάξατε αὐτῇ, καί γε παραβάλλοντες παραβαλεῖτε ἐκ τῶν βεβουνισμένων·","lemmas":"καί βαστάζω  αὐτός , καί γε παραβάλλω  ἐκ ὁ  ·"},{"id":492167,"filename":"tlg0527.tlg010.opp-grc2","tokens":"καὶ φάγεται καὶ συλλέξει, καὶ οὐκ ἐπ’ μήσετε αὐτῇ.","lemmas":"καί  καί  , καί οὐ ἐπί  αὐτός ."},{"id":492168,"filename":"tlg0527.tlg010.opp-grc2","tokens":"καὶ συνέλεξεν ἐν τῷ ἀγρῷ ἕως ἑσπέρας, καὶ ἐράβδισεν ἃ συνέλεξεν, καὶ ἐγενήθη ὡς οἰφὶ κριθῶν.","lemmas":"καί συλλέγω ἐν ὁ ἀγρός ἕως ἑσπέρα , καί  ὅς συλλέγω , καί γίγνομαι ὡς  κριθή ."},{"id":492169,"filename":"tlg0527.tlg010.opp-grc2","tokens":"Καὶ καὶ εἰσῆλθεν εἰς τὴν πόλιν·","lemmas":"καί καί εἰσέρχομαι εἰς ὁ πόλις ·"},{"id":492170,"filename":"tlg0527.tlg010.opp-grc2","tokens":"καὶ εἶδεν ἡ πενθερὰ αὐτῆς ἁ καὶ ἐξενέγκασα ῾Ροὺθ ἔδωκεν αὐτῇ ἃ κατέλιπεν ἐξ ὧν ἐνεπλήσθη.","lemmas":"καί ὁράω ὁ  αὐτός ὁ καί   δίδωμι αὐτός ὅς καταλείπω ἐκ ὅς ἐμπίμπλημι ."},{"id":492171,"filename":"tlg0527.tlg010.opp-grc2","tokens":"καὶ εἶπεν αὐτῇ ἡ πενθερὰ αὐτῆς Ποῦ συνέλεξας σήμερον καὶ ποῦ ἐποίησας;","lemmas":"καί λέγω αὐτός ὁ  αὐτός  συλλέγω σήμερον καί ποῦ ποιέω ;"},{"id":492172,"filename":"tlg0527.tlg010.opp-grc2","tokens":"εἴη ὁ ἐπιγνούς σε εὐλογημένος.","lemmas":"εἰμί ὁ    ."},{"id":492173,"filename":"tlg0527.tlg010.opp-grc2","tokens":"καὶ ἀνήγγειλεν ῾Ροὺθ τῆ πενθερᾷ αὐτῆς ποῦ ἐποίησεν, καὶ εἶπεν Τὸ ὄνομα τοῦ ἀνδρὸς μεθ’ οὗ ἐποίησα σήμερον Βόος.","lemmas":"καί ἀναγγέλλω    αὐτός ποῦ ποιέω , καί λέγω  ὄνομα ὁ ἀνήρ μετά οὗ ποιέω σήμερον  ."},{"id":492174,"filename":"tlg0527.tlg010.opp-grc2","tokens":"καὶ εἶπεν Νωεμεὶν τῇ νύμφη αὐτῆς Εὐλογητός ἐστιν τῷ κυρίῳ, ὅτι οὐκ ἐνκατέλιπεν τὸ ἕλεος αὐτοῦ μετὰ τῶν ζώντων καὶ μετὰ τῶν καὶ εἶπεν αὐτῇ Νωεμείν ᾿Εγγίζει ἡμῖν ὁ ἀνήρ, ἐκ τῶν ἡμᾶς ἐστιν.","lemmas":"καί λέγω  ὁ νύμφη αὐτός  εἰμί τῷ κύριος2 , ὅτι2 οὐ  ὁ ἕλος αὐτός μετά ὁ ζήω καί μετά ὁ καί λέγω αὐτός   ἐγώ ὁ ἀνήρ , ἐκ ὁ  εἰμί ."},{"id":492175,"filename":"tlg0527.tlg010.opp-grc2","tokens":"καὶ εἶπεν ῾Ροὺθ πρὸς τὴν πενθερὰν αὐτῆς καἰ γε ὅτι εἶπεν πρὸς μέ Μετὰ τῶν παιδαρίων μου κολλήθητι ἕως ἂν τελέσωσιν ὅλον τὸν ἀμητὸν ὃς ὑπάρχει μοι.","lemmas":"καί λέγω  πρός ὁ  αὐτός  γε ὅτι2 λέγω πρός  μετά ὁ    ἕως ἄν τελέω ὅλος ὁ  ὅς ὑπάρχω  ."},{"id":492176,"filename":"tlg0527.tlg010.opp-grc2","tokens":"καὶ εἶπεν πρὸς ῾Ροὺθ τὴν νύμφην αὐτῆς ᾿Αγαθόν, θυγάτηρ, ὅτι ἑ μετά τῶν κορασίων αὐτοῦ, καὶ οὐκ ἀπαντήσονταί σοι ἐν ἀγρῷ ἑτέρῳ.","lemmas":"καί λέγω πρός  ὁ νύμφη αὐτός  , θυγάτηρ , ὅτι2 ἕ μετά ὁ  αὐτός , καί οὐ   ἐν ἀγρός ἕτερος ."},{"id":492177,"filename":"tlg0527.tlg010.opp-grc2","tokens":"καὶ προσεκολλήθη ῾Ροὺθ τοῖς κορασίοις βοὸς συλλέγειν ἕως οὗ συνετέλεσεν τὸν θερισμὸν τῶν κριθῶν καὶ τῶν πυρῶν.","lemmas":"καί   ὁ   συλλέγω ἕως οὗ συντελέω ὁ θερισμός ὁ κριθή καί ὁ πυρός ."},{"id":492178,"filename":"tlg0527.tlg010.opp-grc2","tokens":"* κοὶ ἐκάθισεν μετὰ τῆς πενθερᾶς αὐτῆς.","lemmas":"*  καθίζω μετά ὁ  αὐτός ."},{"id":492179,"filename":"tlg0527.tlg010.opp-grc2","tokens":"Ειπεν δὲ αὐτῇ Νωεμεὶν ἡ πενθερὰ αὐτῆς Θυγάτηρ, οὐ μὴ σοι ἀνάπαυσιν ἵνα εὖ γένηται σοι;","lemmas":"δέ αὐτός  ὁ  αὐτός θυγάτηρ , οὐ μή  ἀνάπαυσις ἵνα εὖ γίγνομαι σύ ;"},{"id":492180,"filename":"tlg0527.tlg010.opp-grc2","tokens":"καὶ νῦν οὐχὶ Βόος γνώριμος ἡ οὗ ἦς μετὰ τῶν κορασίων αὐτοῦ;","lemmas":"καί νῦν οὐ  γνώριμος ὁ οὗ  μετά ὁ  αὐτός ;"},{"id":492181,"filename":"tlg0527.tlg010.opp-grc2","tokens":"ἰδοὺ αὐτὸς λικμᾷ τὸν ἅλωνα τῶν κριθῶν ταύτῃ τῇ νυκτί.","lemmas":"αὐτός λικμάω ὁ  ὁ κριθή οὗτος ὁ νύξ ."},{"id":492182,"filename":"tlg0527.tlg010.opp-grc2","tokens":"σὺ δὲ λούσῃ καὶ ἀλείψῃ καὶ περιθησεις τὸν ἱματισμόν σου ἐπὶ σέ, καὶ ἀναβήσῃ ἐπὶ τὸν ἅλω·","lemmas":"δέ  καί  καί  ὁ ἱματισμός  ἐπί  , καί ἀναβαίνω ἐπί ὁ  ·"},{"id":492183,"filename":"tlg0527.tlg010.opp-grc2","tokens":"μὴ γνωρισθῇς τῷ ὶ ἕως οὗ συντελέσαι αὐτὸν πιεῖν καὶ φαγεῖν·","lemmas":"μή  τῷ  ἕως οὗ συντελέω αὐτός πίνω καί ἐσθίω ·"},{"id":492184,"filename":"tlg0527.tlg010.opp-grc2","tokens":"καὶ ἱστᾶι ἐν τὼι αὐτὸν καὶ γνώσῃ τὸν τόπον ὅπου κοιμᾶται ἐκεῖ, καὶ ἐλεύσῃ καὶ ἀποκαλύψεις τὰ πρὸς ποδῶν αὐτοῦ καὶ κοιμηθήσῃ, καὶ αὐτὸς ἀπαγγελεῖ σοι αἰ ποιήσεις.","lemmas":"καί  ἐν τῷ ι αὐτός καί γιγνώσκω ὁ τόπος ὅπου κοιμάω ἐκεῖ , καί  καί ἀποκαλύπτω ὁ πρός πούς αὐτός καί  , καί αὐτός    ποιέω ."},{"id":492185,"filename":"tlg0527.tlg010.opp-grc2","tokens":"εἶπεν δὲ ῾Ροὺθ πρὸς αὐτήν αὐτήν Πάντα ἐὰν εἴπῃς ποιήσω.","lemmas":"λέγω δέ  πρός αὐτός αὐτός  ἐάν λέγω ποιέω ."},{"id":492186,"filename":"tlg0527.tlg010.opp-grc2","tokens":"καὶ κατέβη εἰς τὸν ἅλω, καὶ ἐποίησεν κατὰ πάντα ὅσα ἐνετείλατο αὐτῇ ἡ πενθερὰ αὐτῆς.","lemmas":"καί καταβαίνω εἰς ὁ ἁλίσκομαι , καί ποιέω κατά πᾶς ὅσος  αὐτός ὁ  αὐτός ."},{"id":492187,"filename":"tlg0527.tlg010.opp-grc2","tokens":"καὶ ἔφαγεν Βόος καὶ ἠγαθύνθη ἡ καρδία αὐτοῦ, καὶ ἦλθεν κοιμηθῆναι ἐν μερίδι τῆς στοιβῆς·","lemmas":"καί   καί  ὁ καρδία αὐτός , καί ἔρχομαι κοιμάω ἐν μερίς ὁ στοιβή ·"},{"id":492188,"filename":"tlg0527.tlg010.opp-grc2","tokens":"ἡ δὲ ἦλθεν κρυφῆ καὶ ἀπεκάλυψεν τὰ πρὸς ποδῶν αὐτοῦ.","lemmas":"ὁ δέ ἔρχομαι  καί ἀποκαλύπτω ὁ πρός πούς αὐτός ."},{"id":492189,"filename":"tlg0527.tlg010.opp-grc2","tokens":"ἐγένετο δὲ ἐν τῷ μεσονυκτίῳ καὶ ἐξέστη ὁ ἀνὴρ καὶ ἐταράχθη, καὶ ἰδοὺ γυνὴ κοιμᾶται πρὸς ποδῶν αὐτοῦ.","lemmas":"γίγνομαι δέ ἐν ὁ  καί ἐξίστημι ὁ ἀνήρ καί ταράσσω , καί  γυνή κοιμάω πρός πούς αὐτός ."},{"id":492190,"filename":"tlg0527.tlg010.opp-grc2","tokens":"εἰπεν δέ τίς εἰ σύ;","lemmas":"δέ τις εἰ  ;"},{"id":492191,"filename":"tlg0527.tlg010.opp-grc2","tokens":"ἡ δὲ εἶπεν ᾿Εγώ εἰμι ῾Ρούθ ἡ δούλη σου, καὶ περιβαλεῖς τὸ πτερύγιόν σου ἐπὶ τὴν δούλην σου, ὅτι ἀγχιστεὺς εἶ σύ.","lemmas":"ὁ δέ λέγω  εἰμί  ὁ δούλη  , καί  ὁ   ἐπί ὁ δούλη  , ὅτι2 ἀγχιστεύς εἶμι  ."},{"id":492192,"filename":"tlg0527.tlg010.opp-grc2","tokens":"καὶ εἶπεν Βόος Εὐλογημένη σὺ τῷ κυρίῳ θεῷ, θύγατερ, ὅτι ἠγάθυνας τὸ ἐλεός σου τὸ ἔσχατον ὑπὲρ τὸ πρῶτον τὸ μή πορευθῆναι νεανιῶν, εἴτοι πτωχὸς εἴτοι πλούσιος.","lemmas":"καί λέγω    τῷ κύριος2 θεός , θυγάτηρ , ὅτι2  ὁ ἔλεος  ὁ ἔσχατος ὑπέρ ὁ πρῶτος ὁ μή πορεύω  ,  πτωχός  πλούσιος ."},{"id":492193,"filename":"tlg0527.tlg010.opp-grc2","tokens":"καὶ νῦν, θύγατερ, πάντα ὅσα ἐὰν εἴπῃς ποιήσω σοι·","lemmas":"καί νῦν , θυγάτηρ , πᾶς ὅσος ἐάν λέγω ποιέω  ·"},{"id":492194,"filename":"tlg0527.tlg010.opp-grc2","tokens":"οἶδεν γὰρ πᾶσα φυλή λαοῦ μου ὅτι γυνὴ δυνάμεως εἰ σύ.","lemmas":"οἶδα γάρ πᾶς φυλή   ὅτι2 γυνή δύναμις εἰ  ."},{"id":492195,"filename":"tlg0527.tlg010.opp-grc2","tokens":"καὶ ὅτι ἀληθῶς ἀγχιστεὺς ἐγώ εἰμι·","lemmas":"καί ὅτι2 ἀληθής ἀγχιστεύς  εἰμί ·"},{"id":492196,"filename":"tlg0527.tlg010.opp-grc2","tokens":"καί γέ ἐστιν ἀγχιστεὺς ἐγγίων ὑπὲρ ἐμέ.","lemmas":"καί γε εἰμί ἀγχιστεύς  ὑπέρ  ."},{"id":492197,"filename":"tlg0527.tlg010.opp-grc2","tokens":"αὐλίσθητι τὴν νύκτα, καὶ ὦσται τὸ πρωὶ ἐὰν ἀγχιστε΄πυσῃ σε, ἀγαθόν, ἀγχιστευέτω·","lemmas":"ὁ νύξ , καί  ὁ πρωΐ ἐάν   , ἀγαθός ,  ·"},{"id":492198,"filename":"tlg0527.tlg010.opp-grc2","tokens":"ἐὰν δὲ μὴ βούληται ἀγχιστεῦσαί σε, ἀγχιστεύσω σε ἐγώ, ζῇ Κύριος, σὺ εἶ κύριος·","lemmas":"ἐάν δέ μή βούλομαι   ,    , ζήω κύριος2 ,  εἶμι κύριος2 ·"},{"id":492199,"filename":"tlg0527.tlg010.opp-grc2","tokens":"κοιμήθητι ἕως πρωί.","lemmas":"ἑός πρωΐ ."},{"id":492200,"filename":"tlg0527.tlg010.opp-grc2","tokens":"καὶ ἐκοιμήθη πρὸς ποδῶν αὐτοῦ ἕως πρωί·","lemmas":"καί κοιμάω πρός πούς αὐτός ἕως πρωΐ ·"},{"id":492201,"filename":"tlg0527.tlg010.opp-grc2","tokens":"ἡ δὲ ἐνέστη πρὸ τοῦ ἐπιγνῶναι ἄνδρα τὸν πλησίον αὐτοῦ·","lemmas":"ὁ δέ ἐνίστημι πρό ὁ ἐπιγιγνώσκω ἀνήρ ὁ πλησίος αὐτός ·"},{"id":492202,"filename":"tlg0527.tlg010.opp-grc2","tokens":"καὶ εἶπεν Βόος Μὴ γνωσθήτω ὅτι ἦλθεν γυνή εἰς τὴν ἅλωνα.","lemmas":"καί λέγω  μή γιγνώσκω ὅτι2 ἔρχομαι γυνή εἰς ὁ ἅλως ."},{"id":492203,"filename":"tlg0527.tlg010.opp-grc2","tokens":"καὶ εἶπεν αὐτῇ Φέρε τὸ περίζωμα τὸ ἐπάνω σου.","lemmas":"καί λέγω αὐτός  ὁ περίζωμα ὁ ἐπάνω  ."},{"id":492204,"filename":"tlg0527.tlg010.opp-grc2","tokens":"καὶ ἐκρότησεν αὐτό, καὶ ἐμέτρησεν ἕξ κριθῶν καὶ ἐπέθηκεν ἐπ’ αὐτήν·","lemmas":"καί  αὐτός , καί μετρέω  κριθή καί ἐπιτίθημι ἐπί αὐτός ·"},{"id":492205,"filename":"tlg0527.tlg010.opp-grc2","tokens":"καὶ εἰσῆλθεν εἰς τὴν πόλιν.","lemmas":"καί εἰσέρχομαι εἰς ὁ πόλις ."},{"id":492206,"filename":"tlg0527.tlg010.opp-grc2","tokens":"καὶ ῾Ροὺθ εἰσῆλθεν πρὸς τὴν πενθερὰν αὐτῆς·","lemmas":"καί  εἰσέρχομαι πρός ὁ  αὐτός ·"},{"id":492207,"filename":"tlg0527.tlg010.opp-grc2","tokens":"ἡ δὲ εἶπεν αὐτῇ Θύγατερ·","lemmas":"ὁ δέ λέγω αὐτός  ·"},{"id":492208,"filename":"tlg0527.tlg010.opp-grc2","tokens":"καὶ εἶπεν αὐτὴ πάντα ὅσα ἐποίησεν αὐτῇ ὁ ἀνήρ.","lemmas":"καί λέγω αὐτός πᾶς ὅσος ποιέω αὐτός ὁ ἀνήρ ."},{"id":492209,"filename":"tlg0527.tlg010.opp-grc2","tokens":"καὶ εἶπεν οὐτῇ Τὰ ἕξ τῶν κριθῶν ταῦτα ἔδωκέν μοι, ὅτι εἶπεν πρὸς μέ Μὴ εἰσέλθῃς κενὴ πρὸς τὴν πενθεράν σου.","lemmas":"καί λέγω    ὁ κριθή οὗτος δίδωμι ἐγώ , ὅτι2 λέγω πρός  μή εἰσέρχομαι  πρός ὁ   ."},{"id":492210,"filename":"tlg0527.tlg010.opp-grc2","tokens":"ἡ δὲ εἶπεν Κάθου, θύγατερ, ἕως τοῦ ἐπιγνῶναί σε πῶς οὐ πεσεῖται ῥῆμα·","lemmas":"ὁ δέ λέγω  , θυγάτηρ , ἕως ὁ   πῶς οὐ πίπτω ῥῆμα ·"},{"id":492211,"filename":"tlg0527.tlg010.opp-grc2","tokens":"οὐ γὰρ μὴ ἡσυχάσῃ ὁ ἀνὴρ ἕως ἀν’ τελέσῃ τὸ ῥῆμα σήμερον.","lemmas":"οὐ γάρ μή ἡσυχάζω ὁ ἀνήρ ἕως ἀνά ’ τελέω ὁ ῥῆμα  ."},{"id":492212,"filename":"tlg0527.tlg010.opp-grc2","tokens":"Καὶ Βόος ἀνέβη ἐπὶ τὴν πύλην καὶ ἐκάθισεν ἐκεῖ, καὶ ἰδοὺ ὁ ἀγχιστευτὴς παρεπορεύετο ὅν εἶπεν Βόος.","lemmas":"καί  ἀναβαίνω ἐπί ὁ πύλη καί καθίζω ἐκεῖ , καί  ὁ  παραπορεύομαι ὅς λέγω  ."},{"id":492213,"filename":"tlg0527.tlg010.opp-grc2","tokens":"καὶ εἶπεν πρὸς αὐτὸν Βόος ᾿Εκκλίνας κάθισον ὧδε, κρύφιε·","lemmas":"καί λέγω πρός αὐτός   καθίζω ὧδε , κρύφιος ·"},{"id":492214,"filename":"tlg0527.tlg010.opp-grc2","tokens":"κοὶ ἐξέκλινεν καὶ ἐκάθισεν.","lemmas":"ἐκκλίνω καί καθίζω ."},{"id":492215,"filename":"tlg0527.tlg010.opp-grc2","tokens":"καὶ ἔλαβεν Βόος δέκα ἄνδρας ἀπὸ τῶν πρεσβυτέρων τῆς πόλεως καὶ εἶπεν Καθίσατε ὧδε·","lemmas":"καί λαμβάνω   ἀνήρ ἀπό ὁ πρέσβυς ὁ πόλις καί λέγω  ὧδε ·"},{"id":492216,"filename":"tlg0527.tlg010.opp-grc2","tokens":"καὶ ἐκάθισαν.","lemmas":"καί καθίζω ."},{"id":492217,"filename":"tlg0527.tlg010.opp-grc2","tokens":"καὶ εἶπεν Βόοε τῶ τὴν μερίδα τοῦ ἀγροῦ ἥ ἐστιν τοῦ ἀδελφοῦ ἡμῶν τοῦ ἣ δέδοται Νωεμεὶν τῇ ἐπιστρεφούσῃ ἐξ ἀγροῦ Μωάβ, κἀγὼ εἶπα ᾿Αποκαλύψω τὸ οὖς σου λέγων κτῆσαι ἐναντίον τῶν καθημένων καὶ ἐναντίον τῶν πρεσβυτέρων τοῦ λαοῦ μου·","lemmas":"καί λέγω   ὁ μερίς ὁ ἀγρός ὁ εἰμί ὁ ἀδελφός ἐγώ ὁ ὁ δίδωμι  ὁ  ἐκ ἀγρός  ,    ὁ οὖς  λέγω  ἐναντίος ὁ  καί ἐναντίος ὁ πρέσβυς ὁ λαός  ·"},{"id":492218,"filename":"tlg0527.tlg010.opp-grc2","tokens":"εἰ ἀγχιστεύεις, ἀγχίστευε·","lemmas":"εἰ  ,  ·"},{"id":492219,"filename":"tlg0527.tlg010.opp-grc2","tokens":"εἰ δὲ μὴ ἀγχιστεύεις, ἀνάγγειλόν μοι, καὶ γνώσομαι ὅτι οὐκ ἔστιν παρὲξ σοῦ τοῦ ἀγχιστεῦσαι, κἀγώ εἰμι μετὰ σε.","lemmas":"εἰ δέ μή  ,   , καί γιγνώσκω ὅτι2 οὐ εἰμί παρέξ  ὁ  ,  εἰμί μετά  ."},{"id":492220,"filename":"tlg0527.tlg010.opp-grc2","tokens":"ὁ δὲ εἶπεν ᾿Εγώ εἰμι ἀγχιστεύσω.","lemmas":"ὁ δέ λέγω  εἰμί  ."},{"id":492221,"filename":"tlg0527.tlg010.opp-grc2","tokens":"καὶ εἶπεν Βόος Ἐν ἡμέρᾳ τοῦ κτήσασθαί σε τὸν ἀγρὸν ἐκ χειρὸς Νωεμεὶν καὶ παρὰ ῾Ροὺθ τῆς Μωαβείτιδος γυναικὸς τοῦ τεθνηκότος, καὶ αὐτὴν κτήσασθαί σε δεῖ, ὥστε τὸ ὄνομα τοῦ τεθνηκότος ἐπὶ τῆς κληρονομίας αὐτοῦ.","lemmas":"καί λέγω  ἐν ἡμέρα ὁ κτάομαι  ὁ ἀγρός ἐκ χείρ  καί παρά  ὁ  γυνή ὁ ἀποθνῄσκω , καί αὐτός κτάομαι  δέω , ὥστε ὁ ὄνομα ὁ ἀποθνῄσκω ἐπί ὁ κληρονομία αὐτός ."},{"id":492222,"filename":"tlg0527.tlg010.opp-grc2","tokens":"καὶ εἶπεν ὁ ἀγχιστεύς Οὐ δυνήσομαι ἀγχιστεῦσαι ἐμαυτῷ, μή ποτε διαφείρω τὴν κληρονομίαν μου·","lemmas":"καί λέγω ὁ ἀγχιστεύς οὐ δύναμαι  ἐμαυτοῦ , μή ποτε  ὁ κληρονομία  ·"},{"id":492223,"filename":"tlg0527.tlg010.opp-grc2","tokens":"ἀγχίστευσον σεαυτῷ τὴν ἀχγιστείαν μου, ὅτι οὐ δυνήσομαι ἀγχιστεῦσαι.","lemmas":"σεαυτοῦ ὁ   , ὅτι2 οὐ δύναμαι  ."},{"id":492224,"filename":"tlg0527.tlg010.opp-grc2","tokens":"καὶ τοῦτο τὸ δικαίωμα ἔμπροσθεν ἐν τῷ Ἰσραὴλ ἐπὶ τὴν ἀγχιστείαν καὶ ἐπὶ τὸ ἀντάλλαγμα, τοῦ στῆσαι πάντα λόγον·","lemmas":"καί οὗτος ὁ δικαίωμα ἔμπροσθεν ἐν τῷ  ἐπί ὁ ἀγχιστεία καί ἐπί ὁ ἀντάλλαγμα , ὁ ἵστημι πᾶς λόγος ·"},{"id":492225,"filename":"tlg0527.tlg010.opp-grc2","tokens":"καὶ ὑπελύετο ὁ ἀνὴρ τὸ ὑπόδημα αὐτοῦ καὶ ἐδίδου τῷ πλησίον αὐτοῦ τῷ ἀγχιστεύοντι τὴν ἀγχιστείαν αὐτοῦ·","lemmas":"καί  ὁ ἀνήρ ὁ ὑπόδημα αὐτός καί δίδωμι τῷ πλησίος αὐτός ὁ  ὁ ἀγχιστεία αὐτός ·"},{"id":492226,"filename":"tlg0527.tlg010.opp-grc2","tokens":"κοὶ τοῦτο ἦν μαρτύριον ἐν ᾿Ισραήλ.","lemmas":"οὗτος εἰμί μαρτύριον ἐν  ."},{"id":492227,"filename":"tlg0527.tlg010.opp-grc2","tokens":"καὶ εἶπεν ὁ ἀγχιστεὺς τῷ Βόος Κτῆσαι σεαυτῷ τὴν ἀγχιστείαν μου·","lemmas":"καί λέγω ὁ ἀγχιστεύς τῷ   σεαυτοῦ ὁ ἀγχιστεία  ·"},{"id":492228,"filename":"tlg0527.tlg010.opp-grc2","tokens":"καὶ ὑπελύσατο τὸ ὑπόδημα αὐτοῦ κοὶ ἔδωκεν αὐτῷ.","lemmas":"καί  ὁ ὑπόδημα αὐτός  δίδωμι αὐτός ."},{"id":492229,"filename":"tlg0527.tlg010.opp-grc2","tokens":"Καὶ εἶπεν Βόος τοῖς πρεσβυτέροις καὶ παντὶ τῷ λαῷ Μάρτυρρς ὑμεῖς σήμερον ὅτι κέκτημαι πάντα τὰ τοῦ ᾿Αβειμέλεχ καὶ πάντα ὅσα ὑπάρχει τῷ Χελαιὼν καὶ τῷ Μααλὼν ἐκ ωεμείν·","lemmas":"καί λέγω  ὁ πρέσβυς καί πᾶς ὁ λαός   σήμερον ὅτι2 κτάομαι πᾶς ὁ ὁ  καί πᾶς ὅσος ὑπάρχω τῷ  καί τῷ  ἐκ  ·"},{"id":492230,"filename":"tlg0527.tlg010.opp-grc2","tokens":"καί γε ῾Ροὐθ τὴν Μωαβεῖτιν τὴν γυναῖκα Μααλὼν αὐτῷ εἰς γυναῖκα τοῦ ἀναστῆσαι τὸ ὄνομα τοῦ τεθνηκότος ἐπὶ τῆς κληρονομίας αὐτοῦ, καὶ οὐκ ἐξολεθρευθήσεται τὸ ὄνομα τοῦ τεθνηκότος ἐκ τῶν ἀδελφῶν αὐτοῦ καὶ ἐκ τῆς φυλῆς λαοῦ αὐτοῦ.","lemmas":"καί γε  ὁ  ὁ γυνή  αὐτός εἰς γυνή ὁ ἀνίστημι ὁ ὄνομα ὁ ἀποθνῄσκω ἐπί ὁ κληρονομία αὐτός , καί οὐ  ὁ ὄνομα ὁ ἀποθνῄσκω ἐκ ὁ  αὐτός καί ἐκ ὁ φυλή λαός αὐτός ."},{"id":492231,"filename":"tlg0527.tlg010.opp-grc2","tokens":"μάρτυρες ὑμεῖς σήμερον.","lemmas":"μάρτυς  σήμερον ."},{"id":492232,"filename":"tlg0527.tlg010.opp-grc2","tokens":"καὶ εἴποσαν πᾶς ὁ λαὸς οἱ ἐν τῇ πύλῃ Μάρτθρες.","lemmas":"καί  πᾶς ὁ λαός ὁ ἐν ὁ πύλη  ."},{"id":492233,"filename":"tlg0527.tlg010.opp-grc2","tokens":"καὶ οἱ πρεσβύτεροι εἴποσαν Δῴη κύριος τὴν γυναῖκά σου τήν εἰσπορευομένην εἰς τὸν οἶκόν σου ὡς ῾Ραχὴλ καὶ ὡς λείαν, αἳ ᾠκοδόμησαν ἀμφότεραι τὸν οἶκον τοῦ ᾿Ισραὴλ καὶ ἐποίησαν δύναμιν ἐν Ἐφράθα·","lemmas":"καί ὁ πρέσβυς   κύριος2 ὁ γυνή  ὁ  εἰς ὁ οἶκος  ὡς  καί ὡς λεία , ὁ οἰκοδομέω ἀμφότερος ὁ οἶκος ὁ  καί ποιέω δύναμις ἐν  ·"},{"id":492234,"filename":"tlg0527.tlg010.opp-grc2","tokens":"καὶ ἔσται ὄνομα ἐν Βαιθλέεμ.","lemmas":"καί εἰμί ὄνομα ἐν  ."},{"id":492235,"filename":"tlg0527.tlg010.opp-grc2","tokens":"καὶ γένοιτο ὁ οἰκός σου ὡς ὁ οἶκος Φάρες, ὃν ἔτεκεν Θαμὰρ τῷ ᾿Ιούδᾳ, ἐκ τοῦ σπέρματος οὗ δώσει Κύριός σοι ἐκ τῆς παιδίσκης ταύτης.","lemmas":"καί  ὁ ἔοικα  ὡς ὁ οἶκος  , ὅς τίκτω  τῷ  , ἐκ ὁ σπέρμα οὗ δίδωμι κύριος2  ἐκ ὁ παιδίσκη οὗτος ."},{"id":492236,"filename":"tlg0527.tlg010.opp-grc2","tokens":"Καὶ ἔλαβεν Βόος τὴν ῾Ρούθ, καὶ ἔδωκεν αὐτὴ Κύριος κύησιν, κα ἔτεκεν υἱόν.","lemmas":"καί λαμβάνω  ὁ  , καί δίδωμι αὐτός κύριος2 κύησις ,  τίκτω υἱός ."},{"id":492237,"filename":"tlg0527.tlg010.opp-grc2","tokens":"καὶ εἶπαν αἱ γυναῖκες πρὸς Νωεμείν Εὐλογητὸς κύριος ὅς οὐ κατέλυσέ σοι σήμερον τὸν ἀγχιστέα, καὶ καλέσαι τὸ ὄνομάσου ἐν ᾿Ισραήλ·","lemmas":"καί λέγω ὁ γυνή πρός  εὐλογητός κύριος2 ὅς οὐ καταλύω  σήμερον ὁ  , καί καλέω ὁ  ἐν  ·"},{"id":492238,"filename":"tlg0527.tlg010.opp-grc2","tokens":"καὶ ἱστᾶι σοι εἰς ἐπιστρέφοντα ψυχὴν καὶ τοῦ διαθρέψαι τὴν πολιάν σου, ὅτι ἡ νύμφη ἡ ἀγαπήσασά σε ἔτεκεν αὐτὸν, ἥ ἐστιν ἀγαθή σοι ὑπὲρ ἑπτὰ υἱούς.","lemmas":"καί   εἰς ἐπιστρέφω ψυχή καί ὁ  ὁ πολιά  , ὅτι2 ὁ νύμφη ὁ   τίκτω αὐτός , ὁ εἰμί ἀγαθός  ὑπέρ  υἱός ."},{"id":492239,"filename":"tlg0527.tlg010.opp-grc2","tokens":"καὶ ἔλαβεν Νωεμεὶν τὸ παιδίον καὶ ἔθηκεν εἰς τὸν κόλπον αὐτῆς, καὶ ἐγενήθη αὐτῷ εἰς τιθηνόν.","lemmas":"καί λαμβάνω  ὁ παιδίον καί τίθημι εἰς ὁ κόλπος αὐτός , καί γίγνομαι αὐτός εἰς  ."},{"id":492240,"filename":"tlg0527.tlg010.opp-grc2","tokens":"καὶ ἐκάλεσαν αὐτοῦ αἱ γείτονες ὄνομα λέγουσαι ᾿Ετέχθη υἱὸς τῆ Νωεμείν, καὶ ἐκάλεσαν τὸ ὄνομα αὐτοῦ Ὤβήδ·","lemmas":"καί καλέω αὐτός ὁ γείτων ὄνομα λέγω  υἱός   , καί καλέω ὁ ὄνομα αὐτός  ·"},{"id":492241,"filename":"tlg0527.tlg010.opp-grc2","tokens":"οὗτος πατὴρ ᾿Ιεσσαὶ πατρὸς Δαυείδ.","lemmas":"οὗτος πατήρ  πατήρ  ."},{"id":492242,"filename":"tlg0527.tlg010.opp-grc2","tokens":"Καὶ αὗται αἱ γενέσεις Φάρες·","lemmas":"καί οὗτος ὁ γένεσις  ·"}]